discoverhue/__init__.py
discoverhue/discoverhue.py
discoverhue/ssdp.py
discoverhue-1.0.2.dist-info/DESCRIPTION.rst
discoverhue-1.0.2.dist-info/METADATA
discoverhue-1.0.2.dist-info/RECORD
discoverhue-1.0.2.dist-info/WHEEL
discoverhue-1.0.2.dist-info/metadata.json
discoverhue-1.0.2.dist-info/top_level.txt
