Metadata-Version: 2.0
Name: discoverhue
Version: 1.0.2
Summary: Auto discovery of Hue bridges
Home-page: https://github.com/Overboard/discoverhue
Author: Overboard
Author-email: amwroute-git@yahoo.com
License: MIT
Keywords: philips hue
Platform: UNKNOWN
Classifier: Development Status :: 4 - Beta
Classifier: Intended Audience :: Developers
Classifier: License :: OSI Approved :: MIT License
Classifier: Programming Language :: Python :: 3
Classifier: Programming Language :: Python :: 3.5
Classifier: Programming Language :: Python :: 3.6
Requires-Dist: httpfind
